h3ronpy-0.22.0.dist-info/METADATA
h3ronpy-0.22.0.dist-info/WHEEL
h3ronpy-0.22.0.dist-info/licenses/LICENSE.txt
h3ronpy/polars.py
h3ronpy/__init__.py
h3ronpy/pandas/__init__.py
h3ronpy/pandas/raster.py
h3ronpy/pandas/vector.py
h3ronpy/raster.py
h3ronpy/vector.py
h3ronpy/h3ronpyrs.abi3.so
h3ronpy-0.22.0.dist-info/RECORD
