Metadata-Version: 2.3
Name: h3ronpy
Version: 0.22.0
Classifier: Programming Language :: Python :: 3
Classifier: Topic :: Scientific/Engineering :: GIS
Classifier: License :: OSI Approved :: MIT License
Requires-Dist: numpy
Requires-Dist: arro3-core >=0.4
Requires-Dist: polars >=1 ; extra == 'polars'
Requires-Dist: geopandas >=1 ; extra == 'pandas'
Requires-Dist: pyarrow >=15 ; extra == 'pandas'
Requires-Dist: rasterio >=1.4 ; extra == 'test'
Requires-Dist: shapely >=1.7 ; extra == 'test'
Requires-Dist: pytest >=6 ; extra == 'test'
Requires-Dist: h3 <4 ; extra == 'test'
Requires-Dist: pytest-benchmark ; extra == 'test'
Requires-Dist: pyarrow >=15 ; extra == 'test'
Provides-Extra: polars
Provides-Extra: pandas
Provides-Extra: test
License-File: LICENSE.txt
Summary: Data science toolkit for the H3 geospatial grid
Keywords: geo,spatial,h3,arrow,python
Home-Page: https://github.com/nmandery/h3ronpy
Author: Nico Mandery <nico@nmandery.net>
Author-email: Nico Mandery <nico@nmandery.net>
License: MIT
Project-URL: Source Code, https://github.com/nmandery/h3ronpy
